flux_batch/__init__.py
flux_batch/jobspec.py
flux_batch/models.py
flux_batch/submit.py
flux_batch/version.py
flux_batch/logger/__init__.py
flux_batch/logger/generate.py
flux_batch/logger/logger.py
flux_batch/script/__init__.py
flux_batch/script/save_logs.sh
flux_batch/service/__init__.py
flux_batch/service/scribe.py
flux_batch/service/scribe/__init__.py
flux_batch/service/scribe/__main__.py
flux_batch/service/scribe/database.py
flux_batch/service/scribe/models.py
flux_batch/service/scribe/template.py
flux_batch/utils/__init__.py
flux_batch/utils/fileio.py
flux_batch/utils/text.py
flux_batch/utils/timer.py
flux_batch-0.0.12.dist-info/LICENSE
flux_batch-0.0.12.dist-info/METADATA
flux_batch-0.0.12.dist-info/NOTICE
flux_batch-0.0.12.dist-info/WHEEL
flux_batch-0.0.12.dist-info/entry_points.txt
flux_batch-0.0.12.dist-info/top_level.txt
flux_batch-0.0.12.dist-info/RECORD
