Metadata-Version: 2.1
Name: flux-batch
Version: 0.0.12
Summary: Python SDK for flux batch jobs and services
Home-page: https://github.com/converged-computing/flux-batch
Author: Vanessa Sochat
Author-email: vsoch@users.noreply.github.com
Maintainer: Vanessa Sochat
License: LICENSE
Keywords: flux,flux framework,hpc,batch,workloads
Classifier: Intended Audience :: Science/Research
Classifier: Intended Audience :: Developers
Classifier: License :: OSI Approved :: MIT License
Classifier: Programming Language :: C
Classifier: Programming Language :: Python
Classifier: Topic :: Software Development
Classifier: Topic :: Scientific/Engineering
Classifier: Operating System :: Unix
Classifier: Programming Language :: Python :: 3.11
License-File: LICENSE
License-File: NOTICE
Requires-Dist: pyyaml
Requires-Dist: ply
Provides-Extra: all
Requires-Dist: pyyaml ; extra == 'all'
Requires-Dist: ply ; extra == 'all'
Requires-Dist: pytest >=4.6.2 ; extra == 'all'
Requires-Dist: sqlalchemy ; extra == 'all'
Requires-Dist: rich ; extra == 'all'
Provides-Extra: scribe
Requires-Dist: sqlalchemy ; extra == 'scribe'
Requires-Dist: rich ; extra == 'scribe'
